Metadata-Version: 2.1
Name: custom-signxml
Version: 3.2.3
Summary: Python XML Signature and XAdES library: Original work from Andrey Kislyuk, forked and targetted for pull request.
Home-page: https://github.com/datastyx-dev/signxml.git
Author: Andrey Kislyuk
Author-email: dev@datastyx.com
License: Apache Software License
Platform: MacOS X
Platform: Posix
Classifier: Intended Audience :: Developers
Classifier: License :: OSI Approved :: Apache Software License
Classifier: Operating System :: MacOS :: MacOS X
Classifier: Operating System :: POSIX
Classifier: Programming Language :: Python
Classifier: Programming Language :: Python :: 3.7
Classifier: Programming Language :: Python :: 3.8
Classifier: Programming Language :: Python :: 3.9
Classifier: Programming Language :: Python :: 3.10
Classifier: Programming Language :: Python :: 3.11
Classifier: Programming Language :: Python :: 3.12
Classifier: Topic :: Software Development :: Libraries :: Python Modules
Requires-Python: >=3.7
License-File: LICENSE
License-File: NOTICE
Requires-Dist: lxml <6,>=4.5.0
Requires-Dist: cryptography >=3.4.8
Requires-Dist: pyOpenSSL >=19.0.0
Requires-Dist: certifi >=2019.11.28
Provides-Extra: tests
Requires-Dist: ruff ; extra == 'tests'
Requires-Dist: coverage ; extra == 'tests'
Requires-Dist: build ; extra == 'tests'
Requires-Dist: wheel ; extra == 'tests'
Requires-Dist: mypy ; extra == 'tests'
Requires-Dist: lxml-stubs ; extra == 'tests'
